ai_alchemy/__init__.py
ai_alchemy/core/__init__.py
ai_alchemy/core/ai.py
ai_alchemy/core/cast.py
ai_alchemy/core/py.typed
ai_alchemy-1.0.1.dist-info/WHEEL
ai_alchemy-1.0.1.dist-info/METADATA
ai_alchemy-1.0.1.dist-info/RECORD
