Metadata-Version: 2.1
Name: ai-alchemy
Version: 1.0.1
Summary: Lightweight package for arbitrary data transformation and validation using AI models and first class python libraries like Pandas and Pydantic.
Author: Josh Mogil
Requires-Python: >=3.10,<4.0
Classifier: Programming Language :: Python :: 3
Classifier: Programming Language :: Python :: 3.10
Classifier: Programming Language :: Python :: 3.11
Requires-Dist: openai (>=1.30.1,<2.0.0)
Requires-Dist: pandas-stubs (>=2.2.2.240514,<3.0.0.0)
Requires-Dist: pydantic (>=2.7.1,<3.0.0)
Requires-Dist: requests (>=2.31.0,<3.0.0)
